obs_automation/__init__.py
obs_automation/controller.py
obs_automation/_impl/__init__.py
obs_automation/_impl/client_manager.py
obs_automation/_impl/streamer.py
obs_automation/_impl/video_source.py
obs_automation-0.1.7.dist-info/METADATA
obs_automation-0.1.7.dist-info/WHEEL
obs_automation-0.1.7.dist-info/top_level.txt
obs_automation-0.1.7.dist-info/RECORD
