Metadata-Version: 2.4
Name: obs-automation
Version: 0.1.7
Summary: A clean interface library for automating OBS streaming via obsws-python
Author-email: Anshul Nigam <anshul.nigam@loco.com>
License: MIT
Project-URL: Homepage, https://github.com/getloconow/obs-automation
Project-URL: Repository, https://github.com/yourusername/obs-automation
Project-URL: Issues, https://github.com/yourusername/obs-automation/issues
Requires-Python: >=3.8
Requires-Dist: obsws-python>=1.7.0
